archivy_git/__init__.py
archivy_git-0.1.4.dist-info/METADATA
archivy_git-0.1.4.dist-info/WHEEL
archivy_git-0.1.4.dist-info/entry_points.txt
archivy_git-0.1.4.dist-info/top_level.txt
archivy_git-0.1.4.dist-info/RECORD
