Metadata-Version: 2.1
Name: archivy-git
Version: 0.1.4
Summary: Archivy extension to integrate your knowledge base as a syncable git repository with version control.
Home-page: UNKNOWN
Author: Uzay-G
Author-email: halcyon@disroot.org
License: UNKNOWN
Platform: UNKNOWN
Classifier: Programming Language :: Python :: 3
Classifier: License :: OSI Approved :: MIT License
Requires-Dist: archivy
Requires-Dist: click
Requires-Dist: gitpython
